sphinxter/__init__.py
sphinxter/document.py
sphinxter/reader.py
sphinxter/unittest.py
sphinxter/writer.py
sphinxter-0.1.7.dist-info/LICENSE.txt
sphinxter-0.1.7.dist-info/METADATA
sphinxter-0.1.7.dist-info/WHEEL
sphinxter-0.1.7.dist-info/top_level.txt
sphinxter-0.1.7.dist-info/RECORD
