Metadata-Version: 2.1
Name: sphinxter
Version: 0.1.7
Summary: Autodoc converting YAML docstrings and code comments to sphinx documentation
Home-page: https://sphinxter.readthedocs.io/en/0.1.7/
Download-URL: https://github.com/gaf3/sphinxter
Author: Gaffer Fitch
Author-email: sphinxter@gaf3.com
Classifier: Programming Language :: Python :: 3
Classifier: License :: OSI Approved :: MIT License
License-File: LICENSE.txt
Requires-Dist: Sphinx ==5.1.1
Requires-Dist: PyYAML >=6.0.1
